{
  "groupings": {
  },
  "providing": {
  },
  "attributes": {
    "rightscale/monitoring/collectd_plugins": {
      "required": "recommended",
      "type": "array",
      "calculated": false,
      "display_name": "RightScale Monitoring Plugins",
      "description": "An array of collectd plugins to enable.",
      "choice": [

      ],
      "default": [
        "cpu",
        "df",
        "disk",
        "load",
        "memory",
        "processes",
        "swap",
        "users"
      ],
      "recipes": [
        "rightscale::monitoring"
      ]
    },
    "collectd/collectd_web/hostname": {
      "required": "optional",
      "type": "string",
      "calculated": false,
      "display_name": "collectd_web hostname",
      "description": "The collectd_web hostname.",
      "choice": [

      ],
      "default": "collectd",
      "recipes": [
        "collectd::collectd_web"
      ]
    },
    "rightscale/tags/remove": {
      "required": "optional",
      "type": "array",
      "calculated": false,
      "display_name": "RightScale Tags Remove",
      "description": "An array of RightScale tags to remove from the node.",
      "choice": [

      ],
      "recipes": [
        "rightscale::remove_tags"
      ]
    },
    "collectd/interval": {
      "required": "optional",
      "type": "string",
      "calculated": false,
      "display_name": "collectd Polling Interval",
      "description": "The collectd interval setting value.",
      "choice": [

      ],
      "default": "20",
      "recipes": [
        "collectd::default"
      ]
    },
    "collectd/read_threads": {
      "required": "optional",
      "type": "string",
      "calculated": false,
      "display_name": "collectd Read Threads",
      "description": "The collectd read threads setting value.",
      "choice": [

      ],
      "default": "5",
      "recipes": [
        "collectd::default"
      ]
    },
    "collectd/servers": {
      "required": "required",
      "type": "string",
      "calculated": false,
      "display_name": "collectd Servers",
      "description": "The collectd servers to send to as a client.",
      "choice": [

      ],
      "recipes": [
        "rightscale::default"
      ]
    },
    "collectd/fqdn_lookup": {
      "required": "optional",
      "type": "string",
      "calculated": false,
      "display_name": "collectd FQDNLookup",
      "description": "The collectd FQDNLookup setting value.",
      "choice": [
        "true",
        "false"
      ],
      "default": "true",
      "recipes": [
        "collectd::default",
        "rightscale::default"
      ]
    },
    "collectd/hostname": {
      "required": "optional",
      "type": "string",
      "calculated": false,
      "display_name": "collectd Hostname",
      "description": "The collectd Hostname setting value.",
      "choice": [

      ],
      "recipes": [
        "collectd::default",
        "rightscale::default"
      ]
    },
    "collectd/collectd_web/path": {
      "required": "optional",
      "type": "string",
      "calculated": false,
      "display_name": "collectd_web path",
      "description": "The collectd_web install path.",
      "choice": [

      ],
      "default": "/srv/collectd_web",
      "recipes": [
        "collectd::collectd_web"
      ]
    },
    "rightscale/tags/add": {
      "required": "optional",
      "type": "array",
      "calculated": false,
      "display_name": "RightScale Tags Add",
      "description": "An array of RightScale tags to add to the node.",
      "choice": [

      ],
      "recipes": [
        "rightscale::add_tags"
      ]
    }
  },
  "replacing": {
  },
  "recommendations": {
  },
  "long_description": "Description\n===========\n\nRequirements\n============\n\nAttributes\n==========\n\nUsage\n=====\n\n",
  "license": "Apache 2.0",
  "name": "rightscale",
  "description": "Installs/Configures a Rightscale Server node.",
  "conflicting": {
  },
  "suggestions": {
  },
  "platforms": {
  },
  "maintainer_email": "chris@xhost.com.au",
  "dependencies": {
    "collectd": ">= 0.0.0",
    "rest_connection": ">= 0.0.0"
  },
  "maintainer": "Chris Fordham",
  "version": "0.0.1",
  "recipes": {
    "rightscale::enforce_path_sanity": "Enforces PATH sanity.",
    "rightscale::remove_tags": "Remove tags on the node.",
    "rightscale::tools": "Installs RightScale Tools (RubyGem).",
    "rightscale::add_sandbox_to_path": "Adds the RightLink sandbox to PATH.",
    "rightscale::default": "Sets up RightScale Monitoring, installs RightScale Tools and adds RightScale Server tags.",
    "rightscale::list_tags": "Lists tags on the node.",
    "rightscale::add_tags": "Adds tags to the node.",
    "rightscale::monitoring": "Sets up and configures RightScale Monitoring (collectd).",
    "rightscale::server_tags": "Sets RightScale Server tags."
  }
}